{"_type":"export","__export_format":4,"__export_date":"2023-01-16T22:49:14.064Z","__export_source":"insomnia.desktop.app:v2022.7.2","resources":[{"_id":"req_b454faaeaf76456b8256bffa855ef318","parentId":"fld_c98f4d911c9c4bb5be89bafb1b359d3d","modified":1673907933219,"created":1673811401017,"url":"{{ _.host }}/auth/login","name":"Authentication User","description":"","method":"POST","body":{"mimeType":"application/json","text":"{\n\t\"email\": \"Ernestina.McKenzie@hotmail.com\",\n\t\"password\": \"aS_RhgX2S071Rf4\"\n}"},"parameters":[],"headers":[{"name":"Content-Type","value":"application/json"}],"authentication":{},"metaSortKey":-1673554828389.5,"isPrivate":false,"settingStoreCookies":true,"settingSendCookies":true,"settingDisableRenderRequestBody":false,"settingEncodeUrl":true,"settingRebuildPath":true,"settingFollowRedirects":"global","_type":"request"},{"_id":"fld_c98f4d911c9c4bb5be89bafb1b359d3d","parentId":"wrk_820be25d650a4b6c8fb3cdf6d4145c18","modified":1673828782791,"created":1673828782791,"name":"Authentication","description":"","environment":{},"environmentPropertyOrder":null,"metaSortKey":-1673828782791,"_type":"request_group"},{"_id":"wrk_820be25d650a4b6c8fb3cdf6d4145c18","parentId":null,"modified":1673668568713,"created":1673668568713,"name":"Architects","description":"","scope":"collection","_type":"workspace"},{"_id":"req_3c3c51b0ff6545d6b061a4bb56577ded","parentId":"fld_b2b105ed5a97450590575a234c8978e1","modified":1673833646519,"created":1673668578323,"url":"{{ _.host }}/users","name":"Get All Users","description":"","method":"GET","body":{},"parameters":[],"headers":[],"authentication":{"type":"bearer","token":"{{ _.token }}","disabled":false,"prefix":""},"metaSortKey":-1673668578323,"isPrivate":false,"settingStoreCookies":true,"settingSendCookies":true,"settingDisableRenderRequestBody":false,"settingEncodeUrl":true,"settingRebuildPath":true,"settingFollowRedirects":"global","_type":"request"},{"_id":"fld_b2b105ed5a97450590575a234c8978e1","parentId":"wrk_820be25d650a4b6c8fb3cdf6d4145c18","modified":1673668576522,"created":1673668576522,"name":"Users","description":"","environment":{},"environmentPropertyOrder":null,"metaSortKey":-1673668576522,"_type":"request_group"},{"_id":"req_4fe4d88bffbe461890d7279af384b51d","parentId":"fld_b2b105ed5a97450590575a234c8978e1","modified":1673903365898,"created":1673749358676,"url":"{{ _.host }}/users/7e635712-31cb-4d98-826d-b794f9f448a0","name":"Get User","description":"","method":"GET","body":{},"parameters":[],"headers":[],"authentication":{"type":"bearer","token":"{{ _.token }}"},"metaSortKey":-1673605819739,"isPrivate":false,"settingStoreCookies":true,"settingSendCookies":true,"settingDisableRenderRequestBody":false,"settingEncodeUrl":true,"settingRebuildPath":true,"settingFollowRedirects":"global","_type":"request"},{"_id":"req_34aa002f4a1d4a12b330f623123b2486","parentId":"fld_b2b105ed5a97450590575a234c8978e1","modified":1673890625698,"created":1673751358868,"url":"{{ _.host }}/users/fef1dc3e-2f08-41ae-a369-ccffd7c32a73","name":"Delete User","description":"","method":"DELETE","body":{},"parameters":[],"headers":[],"authentication":{"type":"bearer","token":"{{ _.token }}"},"metaSortKey":-1673574440447,"isPrivate":false,"settingStoreCookies":true,"settingSendCookies":true,"settingDisableRenderRequestBody":false,"settingEncodeUrl":true,"settingRebuildPath":true,"settingFollowRedirects":"global","_type":"request"},{"_id":"req_9649f33bc4424d089689858993ffaf9d","parentId":"fld_b2b105ed5a97450590575a234c8978e1","modified":1673907988570,"created":1673761538668,"url":"{{ _.host }}/users","name":"Create User","description":"","method":"POST","body":{"mimeType":"application/json","text":"{\n\t\"name\": \"Russell Fritsch\",\n  \"email\": \"Lucas.Fisher@hotmail.com\",\n  \"phone\": \"258-693-3428\",\n  \"password\": \"EgcCP1z2ehfGsT7\",\n\t\"age\": 25,\n  \"role\": \"architect\",\n\t\"genre\": \"B\"\n}"},"parameters":[],"headers":[{"name":"Content-Type","value":"application/json"}],"authentication":{},"metaSortKey":-1673558750801,"isPrivate":false,"settingStoreCookies":true,"settingSendCookies":true,"settingDisableRenderRequestBody":false,"settingEncodeUrl":true,"settingRebuildPath":true,"settingFollowRedirects":"global","_type":"request"},{"_id":"req_fb5dbc8cbda54235a09025fa65501c7b","parentId":"fld_b2b105ed5a97450590575a234c8978e1","modified":1673771620588,"created":1673761747248,"url":"{{ _.host }}/users/0409768f-6355-4cf8-b770-e814e04abc97","name":"Update User","description":"","method":"PATCH","body":{"mimeType":"application/json","text":"{\n\t\"name\": \"Matthew\",\n\t\"email\": \"math@email.com\",\n\t\"phone\": \"47 9 6580-5888\",\n\t\"genre\": \"M\",\n\t\"age\": 21,\n\t\"role\": \"client\"\n}"},"parameters":[],"headers":[{"name":"Content-Type","value":"application/json"}],"authentication":{},"metaSortKey":-1673550905978,"isPrivate":false,"settingStoreCookies":true,"settingSendCookies":true,"settingDisableRenderRequestBody":false,"settingEncodeUrl":true,"settingRebuildPath":true,"settingFollowRedirects":"global","_type":"request"},{"_id":"req_4dc6df14b62c4fce8728183bc6130ca4","parentId":"fld_4e61e9c15c0b448f8379c33679f7a316","modified":1673851631548,"created":1673774211405,"url":"{{ _.host }}/forms","name":"Get All Forms","description":"","method":"GET","body":{},"parameters":[],"headers":[],"authentication":{"type":"bearer","token":"{{ _.token }}"},"metaSortKey":-1673668578323,"isPrivate":false,"settingStoreCookies":true,"settingSendCookies":true,"settingDisableRenderRequestBody":false,"settingEncodeUrl":true,"settingRebuildPath":true,"settingFollowRedirects":"global","_type":"request"},{"_id":"fld_4e61e9c15c0b448f8379c33679f7a316","parentId":"wrk_820be25d650a4b6c8fb3cdf6d4145c18","modified":1673774211400,"created":1673774211400,"name":"Forms","description":"","environment":{},"environmentPropertyOrder":null,"metaSortKey":-1673558209035,"_type":"request_group"},{"_id":"req_7169a1b02c0745ca9b1ac2f1e44c6cf9","parentId":"fld_4e61e9c15c0b448f8379c33679f7a316","modified":1673851880799,"created":1673851792738,"url":"{{ _.host }}/forms/archiveds","name":"Get Forms Archiveds","description":"","method":"GET","body":{},"parameters":[],"headers":[],"authentication":{"type":"bearer","token":"{{ _.token }}"},"metaSortKey":-1673637199031,"isPrivate":false,"settingStoreCookies":true,"settingSendCookies":true,"settingDisableRenderRequestBody":false,"settingEncodeUrl":true,"settingRebuildPath":true,"settingFollowRedirects":"global","_type":"request"},{"_id":"req_b5d765c8530b44b895b1b8427355f7ab","parentId":"fld_4e61e9c15c0b448f8379c33679f7a316","modified":1673852063017,"created":1673774211411,"url":"{{ _.host }}/forms/35ae0d00-6100-4680-a314-771fb60aaf4d","name":"Get Form","description":"","method":"GET","body":{},"parameters":[],"headers":[],"authentication":{"type":"bearer","token":"{{ _.token }}"},"metaSortKey":-1673605819739,"isPrivate":false,"settingStoreCookies":true,"settingSendCookies":true,"settingDisableRenderRequestBody":false,"settingEncodeUrl":true,"settingRebuildPath":true,"settingFollowRedirects":"global","_type":"request"},{"_id":"req_141979f9f1e4414684e85cd5efbf0921","parentId":"fld_4e61e9c15c0b448f8379c33679f7a316","modified":1673909034108,"created":1673774211416,"url":"{{ _.host }}/forms/0eca6b1f-088a-4591-879e-9803207ce39f","name":"Delete Form","description":"","method":"DELETE","body":{},"parameters":[],"headers":[],"authentication":{"type":"bearer","token":"{{ _.token }}"},"metaSortKey":-1673574440447,"isPrivate":false,"settingStoreCookies":true,"settingSendCookies":true,"settingDisableRenderRequestBody":false,"settingEncodeUrl":true,"settingRebuildPath":true,"settingFollowRedirects":"global","_type":"request"},{"_id":"req_3d6c240b9dfb4f5b931a36ee9a3c9676","parentId":"fld_4e61e9c15c0b448f8379c33679f7a316","modified":1673909008194,"created":1673774211421,"url":"{{ _.host }}/forms ","name":"Create Form","description":"","method":"POST","body":{"mimeType":"application/json","text":"{\n\t\"title\": \"Formulário de requisição\",\n\t\"description\": \"Lorem Ipsum is simply dummy text of the printing and typesetting industry. Lorem Ipsum has been the industry's standard dummy text ever since the 1500s, when an unknown printer took a galley of type and scrambled it to make a type specimen book. It has survived not only five centuries, but also the leap into electronic typesetting, remaining essentially unchanged. It was popularised in the 1960s with the release of Letraset sheets containing Lorem Ipsum passages, and more recently with desktop publishing software like Aldus PageMaker including versions of Lorem Ipsum.\",\n\t\"name\": \"João Felipe\",\n\t\"email\": \"joaolipe@email.com\",\n\t\"architectId\": \"93a19ccf-5bcf-481c-b113-41b2f3ae2518\"\n}"},"parameters":[],"headers":[{"name":"Content-Type","value":"application/json"}],"authentication":{"type":"bearer","token":"{{ _.token }}"},"metaSortKey":-1673558750801,"isPrivate":false,"settingStoreCookies":true,"settingSendCookies":true,"settingDisableRenderRequestBody":false,"settingEncodeUrl":true,"settingRebuildPath":true,"settingFollowRedirects":"global","_type":"request"},{"_id":"req_500ac30cbbc74127a49f461a75120367","parentId":"fld_4e61e9c15c0b448f8379c33679f7a316","modified":1673894417723,"created":1673774211425,"url":"{{ _.host }}/forms/d81aae73-6c61-4c3e-8182-da06960a0648","name":"Update Form","description":"","method":"PATCH","body":{"mimeType":"application/json","text":"{\n\t\"title\": \"Formulário de requisição\",\n\t\"description\": \"Lorem Ipsum is simply dummy text of the printing and typesetting industry. Lorem Ipsum has been the industry's standard dummy text ever since the 1500s, when an unknown printer took a galley of type and scrambled it to make a type specimen book. It has survived not only five centuries, but also the leap into electronic typesetting, remaining essentially unchanged. It was popularised in the 1960s with the release of Letraset sheets containing Lorem Ipsum passages, and more recently with desktop publishing software like Aldus PageMaker including versions of Lorem Ipsum.\",\n\"name\": \"João Felipe\"\t\n}"},"parameters":[],"headers":[{"name":"Content-Type","value":"application/json"}],"authentication":{"type":"bearer","token":"{{ _.token }}"},"metaSortKey":-1673550905978,"isPrivate":false,"settingStoreCookies":true,"settingSendCookies":true,"settingDisableRenderRequestBody":false,"settingEncodeUrl":true,"settingRebuildPath":true,"settingFollowRedirects":"global","_type":"request"},{"_id":"env_28a5ba89b2d708d0a3db91fb09e8b6cee80b69ba","parentId":"wrk_820be25d650a4b6c8fb3cdf6d4145c18","modified":1673668568720,"created":1673668568720,"name":"Base Environment","data":{},"dataPropertyOrder":null,"color":null,"isPrivate":false,"metaSortKey":1673668568720,"_type":"environment"},{"_id":"jar_28a5ba89b2d708d0a3db91fb09e8b6cee80b69ba","parentId":"wrk_820be25d650a4b6c8fb3cdf6d4145c18","modified":1673668568723,"created":1673668568723,"name":"Default Jar","cookies":[],"_type":"cookie_jar"},{"_id":"spc_918061ce900f4c4882c66ee0bfb709ff","parentId":"wrk_820be25d650a4b6c8fb3cdf6d4145c18","modified":1673668568714,"created":1673668568714,"fileName":"Architects","contents":"","contentType":"yaml","_type":"api_spec"},{"_id":"env_ca9c3fd5001d48329d5f5c41d87979ba","parentId":"env_28a5ba89b2d708d0a3db91fb09e8b6cee80b69ba","modified":1673908215959,"created":1673668602770,"name":"LocalHost","data":{"host":"localhost:3002","token":"eyJhbGciOiJIUzI1NiIsInR5cCI6IkpXVCJ9.eyJuYW1lIjoiSmFja2llIEhpbGxzIiwiaWQiOiJkOWYwNjk4Yi03MjE0LTQwMDUtYWQ5Yi1jZmMzMjE3YWJiMTYiLCJpYXQiOjE2NzM5MDgyMDIsImV4cCI6MTY3MzkyNjIwMn0.fFNQ883Ur-pe-_ERywZs1ZuR-SPAegVwFZVLm2PP17I"},"dataPropertyOrder":{"&":["host","token"]},"color":"#1f1f1f","isPrivate":false,"metaSortKey":1673668602770,"_type":"environment"}]}